{
  "gitSyncId": "68b68c984bf44f0c6aaa481d_0b084546-53f7-49f5-bb0d-5d9e430a4859",
  "id": "Anasayfa_Select_public_araclar1",
  "pluginId": "postgres-plugin",
  "pluginType": "DB",
  "unpublishedAction": {
    "actionConfiguration": {
      "body": "SELECT\n  *\nFROM\n  public.araclar\nWHERE\n  \"model\" ilike '%{{araba_table.searchText}}%'\nORDER BY\n  \"{{araba_table.sortOrder.column || 'id'}}\" {{araba_table.sortOrder.order !== \"desc\" ? \"\" : \"DESC\"}}\nLIMIT\n  {{araba_table.pageSize}}\nOFFSET\n  {{araba_table.pageOffset}}",
      "encodeParamsToggle": true,
      "paginationType": "NONE",
      "pluginSpecifiedTemplates": [
        {
          "value": true
        }
      ],
      "timeoutInMillisecond": 10000
    },
    "confirmBeforeExecute": false,
    "datasource": {
      "id": "Deneme Database",
      "isAutoGenerated": false,
      "name": "Deneme Database",
      "pluginId": "postgres-plugin"
    },
    "dynamicBindingPathList": [
      {
        "key": "body"
      }
    ],
    "name": "Select_public_araclar1",
    "pageId": "Anasayfa",
    "runBehaviour": "MANUAL",
    "userSetOnLoad": false
  }
}